EmailErrorMix/__init__.py
EmailErrorMix/erroremailer.py
EmailErrorMix-0.1.0.dist-info/LICENSE
EmailErrorMix-0.1.0.dist-info/METADATA
EmailErrorMix-0.1.0.dist-info/WHEEL
EmailErrorMix-0.1.0.dist-info/top_level.txt
EmailErrorMix-0.1.0.dist-info/RECORD
