Metadata-Version: 2.1
Name: EmailErrorMix
Version: 0.1.0
Summary: A Python package for automated error notification emails, enhancing software debugging and maintenance.
Home-page: https://github.com/Mathimix7/EmailErrorMix
Author: Mathimix
Author-email: <mathimixich@gmail.com>
License: MIT
Keywords: python,email,error,alerts,maintenance
License-File: LICENSE
